grammatical.py
grammatical-0.2.1.dist-info/LICENSE
grammatical-0.2.1.dist-info/METADATA
grammatical-0.2.1.dist-info/WHEEL
grammatical-0.2.1.dist-info/entry_points.txt
grammatical-0.2.1.dist-info/top_level.txt
grammatical-0.2.1.dist-info/RECORD
