Metadata-Version: 2.1
Name: grammatical
Version: 0.2.1
Summary: Corrects the spelling and grammar of your text using ChatGPT.
Home-page: https://github.com/pncnmnp/grammatical
Author: Parth Parikh
Author-email: parthparikh1999p@gmail.com
Classifier: Programming Language :: Python :: 3
Classifier: License :: OSI Approved :: MIT License
Classifier: Operating System :: OS Independent
Requires-Python: >=3.7
License-File: LICENSE
Requires-Dist: click
Requires-Dist: openai
Requires-Dist: pyperclip
Requires-Dist: rich
Requires-Dist: setuptools
